hybridbosse/__init__.py
hybridbosse/LandBOSSE/__init__.py
hybridbosse/LandBOSSE/main.py
hybridbosse/LandBOSSE/setup.py
hybridbosse/LandBOSSE/landbosse/excelio/CsvGenerator.py
hybridbosse/LandBOSSE/landbosse/excelio/GridSearchTree.py
hybridbosse/LandBOSSE/landbosse/excelio/WeatherWindowCSVReader.py
hybridbosse/LandBOSSE/landbosse/excelio/XlsxDataframeCache.py
hybridbosse/LandBOSSE/landbosse/excelio/XlsxFileOperations.py
hybridbosse/LandBOSSE/landbosse/excelio/XlsxGenerator.py
hybridbosse/LandBOSSE/landbosse/excelio/XlsxManagerRunner.py
hybridbosse/LandBOSSE/landbosse/excelio/XlsxOperationException.py
hybridbosse/LandBOSSE/landbosse/excelio/XlsxParallelManagerRunner.py
hybridbosse/LandBOSSE/landbosse/excelio/XlsxReader.py
hybridbosse/LandBOSSE/landbosse/excelio/XlsxSerialManagerRunner.py
hybridbosse/LandBOSSE/landbosse/excelio/XlsxValidator.py
hybridbosse/LandBOSSE/landbosse/excelio/__init__.py
hybridbosse/LandBOSSE/landbosse/landbosse_api/__init__.py
hybridbosse/LandBOSSE/landbosse/landbosse_api/project_list.xlsx
hybridbosse/LandBOSSE/landbosse/landbosse_api/run.py
hybridbosse/LandBOSSE/landbosse/landbosse_api/turbine_scaling.py
hybridbosse/LandBOSSE/landbosse/landbosse_api/project_data/az_rolling.srw
hybridbosse/LandBOSSE/landbosse/landbosse_api/project_data/ge15_public.xlsx
hybridbosse/LandBOSSE/landbosse/model/CollectionCost.py
hybridbosse/LandBOSSE/landbosse/model/CostModule.py
hybridbosse/LandBOSSE/landbosse/model/DefaultMasterInputDict.py
hybridbosse/LandBOSSE/landbosse/model/DevelopmentCost.py
hybridbosse/LandBOSSE/landbosse/model/ErectionCost.py
hybridbosse/LandBOSSE/landbosse/model/FoundationCost.py
hybridbosse/LandBOSSE/landbosse/model/GridConnectionCost.py
hybridbosse/LandBOSSE/landbosse/model/ManagementCost.py
hybridbosse/LandBOSSE/landbosse/model/Manager.py
hybridbosse/LandBOSSE/landbosse/model/SitePreparationCost.py
hybridbosse/LandBOSSE/landbosse/model/SubstationCost.py
hybridbosse/LandBOSSE/landbosse/model/WeatherDelay.py
hybridbosse-0.9.9.2.dist-info/AUTHORS.rst
hybridbosse-0.9.9.2.dist-info/LICENSE
hybridbosse-0.9.9.2.dist-info/METADATA
hybridbosse-0.9.9.2.dist-info/WHEEL
hybridbosse-0.9.9.2.dist-info/top_level.txt
hybridbosse-0.9.9.2.dist-info/RECORD
