Metadata-Version: 2.1
Name: hybridbosse
Version: 0.9.9.2
Summary: Tool for estimating BOS costs for hybrid power plants that share a physical infrastructure
Home-page: https://github.com/parangat94/hybridbosse
Author: Parangat Bhaskar
Author-email: parangat.bhaskar94@gmail.com
License: MIT license
Keywords: HybridBOSSE
Platform: UNKNOWN
Classifier: Development Status :: 2 - Pre-Alpha
Classifier: Intended Audience :: Developers
Classifier: Intended Audience :: Education
Classifier: Intended Audience :: Science/Research
Classifier: License :: OSI Approved :: MIT License
Classifier: Natural Language :: English
Classifier: Programming Language :: Python :: 3.6
Classifier: Programming Language :: Python :: 3.7
Requires-Python: >=3.6
Requires-Dist: pandas (==1.0.3)
Requires-Dist: numpy (==1.17.2)
Requires-Dist: sympy (==1.4)
Requires-Dist: scipy (==1.3.1)
Requires-Dist: xlsxwriter (==1.2.1)
Requires-Dist: xlrd (==1.2.0)
Requires-Dist: pytest (==5.3.5)
Requires-Dist: PyYaml (==5.1.2)
